systems_engineering/__init__.py
systems_engineering/cost_models/README.md
systems_engineering/cost_models/__init__.py
systems_engineering/cost_models/cosysmo.py
systems_engineering/diagrams/__init__.py
systems_engineering/diagrams/diagrams.py
systems_engineering/simulation/__init__.py
systems_engineering/simulation/simulation.py
systems_engineering-0.37.dist-info/METADATA
systems_engineering-0.37.dist-info/WHEEL
systems_engineering-0.37.dist-info/RECORD
