Metadata-Version: 2.3
Name: systems-engineering
Version: 0.37
Summary: Systems Engineering Library (se-lib) Fork
Project-URL: Homepage, http://se-lib.org
Author-email: se-lib Development Team <info@se-lib.org>
Classifier: License :: OSI Approved :: MIT License
Classifier: Operating System :: OS Independent
Classifier: Programming Language :: Python :: 3
Requires-Python: >=3.7
Requires-Dist: graphviz
Requires-Dist: ipython
Requires-Dist: matplotlib
Requires-Dist: netcdf4
Requires-Dist: pandas
Requires-Dist: pysd
Requires-Dist: simpy
